README.md
slacktivate/__init__.py
slacktivate/__version__.py
slacktivate/cli/__main__.py
slacktivate/cli/commands/channels.py
slacktivate/cli/commands/groups.py
slacktivate/cli/commands/users.py
slacktivate/cli/helpers.py
slacktivate/cli/logo.py
slacktivate/helpers/__init__.py
slacktivate/helpers/collections.py
slacktivate/helpers/dict_serializer.py
slacktivate/helpers/photo.py
slacktivate/input/__init__.py
slacktivate/input/config.py
slacktivate/input/helpers.py
slacktivate/input/parsing.py
slacktivate/macros/__init__.py
slacktivate/macros/manage.py
slacktivate/macros/provision.py
slacktivate/slack/__init__.py
slacktivate/slack/classes.py
slacktivate/slack/clients.py
slacktivate/slack/exceptions.py
slacktivate/slack/methods.py
slacktivate/slack/retry.py
slacktivate-0.2.26.dist-info/entry_points.txt
slacktivate-0.2.26.dist-info/LICENSE
slacktivate-0.2.26.dist-info/WHEEL
slacktivate-0.2.26.dist-info/METADATA
slacktivate-0.2.26.dist-info/RECORD
